LICENSE.txt
README.md
setup.cfg
setup.py
oggy/__init__.py
oggy/main.py
oggy.egg-info/PKG-INFO
oggy.egg-info/SOURCES.txt
oggy.egg-info/dependency_links.txt
oggy.egg-info/requires.txt
oggy.egg-info/top_level.txt