Metadata-Version: 2.1
Name: oggy
Version: 0.1
Summary: Oggy is the boss
Home-page: https://github.com/nikrozine
Download-URL: https://github.com/nikrozine/pypi/archive/refs/tags/v1.tar.gz
Author: umangchaudhary
Author-email: umangchaudhary7@icloud.com
License: MIT
Keywords: SOME,MEANINGFULL,KEYWORDS
Classifier: Development Status :: 3 - Alpha
Classifier: Intended Audience :: Developers
Classifier: Topic :: Software Development :: Build Tools
Classifier: License :: OSI Approved :: MIT License
Classifier: Programming Language :: Python :: 3
Classifier: Programming Language :: Python :: 3.4
Classifier: Programming Language :: Python :: 3.5
Classifier: Programming Language :: Python :: 3.8
License-File: LICENSE.txt
